Workbook

Sheet Dashboard
A1: Controle Financeiro Pessoal - 12 Meses | L1: Filtrar Mês: | N1: Todos
A3: Resumo Mensal
A4: 💵 Salário Líquido | C4: 💼 Rendas Extras (Freelancer) | E4: Total Receitas | G4: ⬇️ Total Despesas | I4: 💲 Disponível no Mês | K4: 🏦 Reserva Financeira | M4: 🎓 Gasto com Estudos
A5: =IF($N$1="Todos", SUMIFS('Lançamentos'!$E$3:$E$500, 'Lançamentos'!$C$3:$C$500, "Salário", 'Lançamentos'!$D$3:$D$500, "Receita"), SUMIFS('Lançamentos'!$E$3:$E$500, 'Lançamentos'!$C$3:$C$500, "Salário", 'Lançamentos'!$D$3:$D$500, "Receita", 'Lançamentos'!$F$3:$F$500, $N$1)) | C5: =IF($N$1="Todos", SUMIFS('Lançamentos'!$E$3:$E$500, 'Lançamentos'!$C$3:$C$500, "Rendas Extras", 'Lançamentos'!$D$3:$D$500, "Receita"), SUMIFS('Lançamentos'!$E$3:$E$500, 'Lançamentos'!$C$3:$C$500, "Rendas Extras", 'Lançamentos'!$D$3:$D$500, "Receita", 'Lançamentos'!$F$3:$F$500, $N$1)) | E5: =IF($N$1="Todos", SUMIFS('Lançamentos'!$E$3:$E$500, 'Lançamentos'!$D$3:$D$500, "Receita"), SUMIFS('Lançamentos'!$E$3:$E$500, 'Lançamentos'!$D$3:$D$500, "Receita", 'Lançamentos'!$F$3:$F$500, $N$1)) | G5: =IF($N$1="Todos", SUMIFS('Lançamentos'!$E$3:$E$500, 'Lançamentos'!$D$3:$D$500, "Despesa"), SUMIFS('Lançamentos'!$E$3:$E$500, 'Lançamentos'!$D$3:$D$500, "Despesa", 'Lançamentos'!$F$3:$F$500, $N$1)) | I5: =E5-G5 | K5: =IF($N$1="Todos", SUMIFS('Lançamentos'!$E$3:$E$500, 'Lançamentos'!$C$3:$C$500, "Reserva"), SUMIFS('Lançamentos'!$E$3:$E$500, 'Lançamentos'!$C$3:$C$500, "Reserva", 'Lançamentos'!$F$3:$F$500, $N$1)) | M5: =IF($N$1="Todos", SUMIFS('Lançamentos'!$E$3:$E$500, 'Lançamentos'!$C$3:$C$500, "Estudos", 'Lançamentos'!$D$3:$D$500, "Despesa"), SUMIFS('Lançamentos'!$E$3:$E$500, 'Lançamentos'!$C$3:$C$500, "Estudos", 'Lançamentos'!$D$3:$D$500, "Despesa", 'Lançamentos'!$F$3:$F$500, $N$1))
K6: (Meta: 20% das receitas)
A7: (Receita principal) | C7: (Projetos e consultoria) | E7: (Salário + Extras) | G7: (Todos os gastos) | I7: (Receitas - Despesas) | K7: ="Atingido: " & TEXT(IF(E5>0, K5/(E5*'Configurações'!$J$2), 0), "0.0%") | M7: (Cursos, livros, faculdade)
A9: Lançamentos | I9: Gastos por Categoria
A10: Data | B10: Descrição | C10: Categoria | D10: Tipo | E10: Valor (R$) | F10: Mês | G10: Observações | I10: Categoria | J10: Valor (R$) | K10: % do Total
A11: =IF('Lançamentos'!A3="","",'Lançamentos'!A3) | B11: =IF('Lançamentos'!B3="","",'Lançamentos'!B3) | C11: =IF('Lançamentos'!C3="","",'Lançamentos'!C3) | D11: =IF('Lançamentos'!D3="","",'Lançamentos'!D3) | E11: =IF('Lançamentos'!E3="","",'Lançamentos'!E3) | F11: =IF('Lançamentos'!F3="","",'Lançamentos'!F3) | G11: =IF('Lançamentos'!G3="","",'Lançamentos'!G3) | I11: Moradia | J11: =IF($N$1="Todos", SUMIFS('Lançamentos'!$E$3:$E$500, 'Lançamentos'!$C$3:$C$500, I11, 'Lançamentos'!$D$3:$D$500, "Despesa"), SUMIFS('Lançamentos'!$E$3:$E$500, 'Lançamentos'!$C$3:$C$500, I11, 'Lançamentos'!$D$3:$D$500, "Despesa", 'Lançamentos'!$F$3:$F$500, $N$1)) | K11: =IF($J$19>0, J11/$J$19, 0)
A12: =IF('Lançamentos'!A4="","",'Lançamentos'!A4) | B12: =IF('Lançamentos'!B4="","",'Lançamentos'!B4) | C12: =IF('Lançamentos'!C4="","",'Lançamentos'!C4) | D12: =IF('Lançamentos'!D4="","",'Lançamentos'!D4) | E12: =IF('Lançamentos'!E4="","",'Lançamentos'!E4) | F12: =IF('Lançamentos'!F4="","",'Lançamentos'!F4) | G12: =IF('Lançamentos'!G4="","",'Lançamentos'!G4) | I12: Alimentação | J12: =IF($N$1="Todos", SUMIFS('Lançamentos'!$E$3:$E$500, 'Lançamentos'!$C$3:$C$500, I12, 'Lançamentos'!$D$3:$D$500, "Despesa"), SUMIFS('Lançamentos'!$E$3:$E$500, 'Lançamentos'!$C$3:$C$500, I12, 'Lançamentos'!$D$3:$D$500, "Despesa", 'Lançamentos'!$F$3:$F$500, $N$1)) | K12: =IF($J$19>0, J12/$J$19, 0)
A13: =IF('Lançamentos'!A5="","",'Lançamentos'!A5) | B13: =IF('Lançamentos'!B5="","",'Lançamentos'!B5) | C13: =IF('Lançamentos'!C5="","",'Lançamentos'!C5) | D13: =IF('Lançamentos'!D5="","",'Lançamentos'!D5) | E13: =IF('Lançamentos'!E5="","",'Lançamentos'!E5) | F13: =IF('Lançamentos'!F5="","",'Lançamentos'!F5) | G13: =IF('Lançamentos'!G5="","",'Lançamentos'!G5) | I13: Transporte | J13: =IF($N$1="Todos", SUMIFS('Lançamentos'!$E$3:$E$500, 'Lançamentos'!$C$3:$C$500, I13, 'Lançamentos'!$D$3:$D$500, "Despesa"), SUMIFS('Lançamentos'!$E$3:$E$500, 'Lançamentos'!$C$3:$C$500, I13, 'Lançamentos'!$D$3:$D$500, "Despesa", 'Lançamentos'!$F$3:$F$500, $N$1)) | K13: =IF($J$19>0, J13/$J$19, 0)
A14: =IF('Lançamentos'!A6="","",'Lançamentos'!A6) | B14: =IF('Lançamentos'!B6="","",'Lançamentos'!B6) | C14: =IF('Lançamentos'!C6="","",'Lançamentos'!C6) | D14: =IF('Lançamentos'!D6="","",'Lançamentos'!D6) | E14: =IF('Lançamentos'!E6="","",'Lançamentos'!E6) | F14: =IF('Lançamentos'!F6="","",'Lançamentos'!F6) | G14: =IF('Lançamentos'!G6="","",'Lançamentos'!G6) | I14: Estudos | J14: =IF($N$1="Todos", SUMIFS('Lançamentos'!$E$3:$E$500, 'Lançamentos'!$C$3:$C$500, I14, 'Lançamentos'!$D$3:$D$500, "Despesa"), SUMIFS('Lançamentos'!$E$3:$E$500, 'Lançamentos'!$C$3:$C$500, I14, 'Lançamentos'!$D$3:$D$500, "Despesa", 'Lançamentos'!$F$3:$F$500, $N$1)) | K14: =IF($J$19>0, J14/$J$19, 0)
A15: =IF('Lançamentos'!A7="","",'Lançamentos'!A7) | B15: =IF('Lançamentos'!B7="","",'Lançamentos'!B7) | C15: =IF('Lançamentos'!C7="","",'Lançamentos'!C7) | D15: =IF('Lançamentos'!D7="","",'Lançamentos'!D7) | E15: =IF('Lançamentos'!E7="","",'Lançamentos'!E7) | F15: =IF('Lançamentos'!F7="","",'Lançamentos'!F7) | G15: =IF('Lançamentos'!G7="","",'Lançamentos'!G7) | I15: Saúde | J15: =IF($N$1="Todos", SUMIFS('Lançamentos'!$E$3:$E$500, 'Lançamentos'!$C$3:$C$500, I15, 'Lançamentos'!$D$3:$D$500, "Despesa"), SUMIFS('Lançamentos'!$E$3:$E$500, 'Lançamentos'!$C$3:$C$500, I15, 'Lançamentos'!$D$3:$D$500, "Despesa", 'Lançamentos'!$F$3:$F$500, $N$1)) | K15: =IF($J$19>0, J15/$J$19, 0)
A16: =IF('Lançamentos'!A8="","",'Lançamentos'!A8) | B16: =IF('Lançamentos'!B8="","",'Lançamentos'!B8) | C16: =IF('Lançamentos'!C8="","",'Lançamentos'!C8) | D16: =IF('Lançamentos'!D8="","",'Lançamentos'!D8) | E16: =IF('Lançamentos'!E8="","",'Lançamentos'!E8) | F16: =IF('Lançamentos'!F8="","",'Lançamentos'!F8) | G16: =IF('Lançamentos'!G8="","",'Lançamentos'!G8) | I16: Lazer | J16: =IF($N$1="Todos", SUMIFS('Lançamentos'!$E$3:$E$500, 'Lançamentos'!$C$3:$C$500, I16, 'Lançamentos'!$D$3:$D$500, "Despesa"), SUMIFS('Lançamentos'!$E$3:$E$500, 'Lançamentos'!$C$3:$C$500, I16, 'Lançamentos'!$D$3:$D$500, "Despesa", 'Lançamentos'!$F$3:$F$500, $N$1)) | K16: =IF($J$19>0, J16/$J$19, 0)
A17: =IF('Lançamentos'!A9="","",'Lançamentos'!A9) | B17: =IF('Lançamentos'!B9="","",'Lançamentos'!B9) | C17: =IF('Lançamentos'!C9="","",'Lançamentos'!C9) | D17: =IF('Lançamentos'!D9="","",'Lançamentos'!D9) | E17: =IF('Lançamentos'!E9="","",'Lançamentos'!E9) | F17: =IF('Lançamentos'!F9="","",'Lançamentos'!F9) | G17: =IF('Lançamentos'!G9="","",'Lançamentos'!G9) | I17: Reserva | J17: =IF($N$1="Todos", SUMIFS('Lançamentos'!$E$3:$E$500, 'Lançamentos'!$C$3:$C$500, I17, 'Lançamentos'!$D$3:$D$500, "Despesa"), SUMIFS('Lançamentos'!$E$3:$E$500, 'Lançamentos'!$C$3:$C$500, I17, 'Lançamentos'!$D$3:$D$500, "Despesa", 'Lançamentos'!$F$3:$F$500, $N$1)) | K17: =IF($J$19>0, J17/$J$19, 0)
A18: =IF('Lançamentos'!A10="","",'Lançamentos'!A10) | B18: =IF('Lançamentos'!B10="","",'Lançamentos'!B10) | C18: =IF('Lançamentos'!C10="","",'Lançamentos'!C10) | D18: =IF('Lançamentos'!D10="","",'Lançamentos'!D10) | E18: =IF('Lançamentos'!E10="","",'Lançamentos'!E10) | F18: =IF('Lançamentos'!F10="","",'Lançamentos'!F10) | G18: =IF('Lançamentos'!G10="","",'Lançamentos'!G10) | I18: Outras Despesas | J18: =IF($N$1="Todos", SUMIFS('Lançamentos'!$E$3:$E$500, 'Lançamentos'!$C$3:$C$500, I18, 'Lançamentos'!$D$3:$D$500, "Despesa"), SUMIFS('Lançamentos'!$E$3:$E$500, 'Lançamentos'!$C$3:$C$500, I18, 'Lançamentos'!$D$3:$D$500, "Despesa", 'Lançamentos'!$F$3:$F$500, $N$1)) | K18: =IF($J$19>0, J18/$J$19, 0)
A19: =IF('Lançamentos'!A11="","",'Lançamentos'!A11) | B19: =IF('Lançamentos'!B11="","",'Lançamentos'!B11) | C19: =IF('Lançamentos'!C11="","",'Lançamentos'!C11) | D19: =IF('Lançamentos'!D11="","",'Lançamentos'!D11) | E19: =IF('Lançamentos'!E11="","",'Lançamentos'!E11) | F19: =IF('Lançamentos'!F11="","",'Lançamentos'!F11) | G19: =IF('Lançamentos'!G11="","",'Lançamentos'!G11) | I19: Total Despesas | J19: =SUM(J11:J18) | K19: =SUM(K11:K18)
A20: =IF('Lançamentos'!A12="","",'Lançamentos'!A12) | B20: =IF('Lançamentos'!B12="","",'Lançamentos'!B12) | C20: =IF('Lançamentos'!C12="","",'Lançamentos'!C12) | D20: =IF('Lançamentos'!D12="","",'Lançamentos'!D12) | E20: =IF('Lançamentos'!E12="","",'Lançamentos'!E12) | F20: =IF('Lançamentos'!F12="","",'Lançamentos'!F12) | G20: =IF('Lançamentos'!G12="","",'Lançamentos'!G12)
A21: =IF('Lançamentos'!A13="","",'Lançamentos'!A13) | B21: =IF('Lançamentos'!B13="","",'Lançamentos'!B13) | C21: =IF('Lançamentos'!C13="","",'Lançamentos'!C13) | D21: =IF('Lançamentos'!D13="","",'Lançamentos'!D13) | E21: =IF('Lançamentos'!E13="","",'Lançamentos'!E13) | F21: =IF('Lançamentos'!F13="","",'Lançamentos'!F13) | G21: =IF('Lançamentos'!G13="","",'Lançamentos'!G13)
A22: =IF('Lançamentos'!A14="","",'Lançamentos'!A14) | B22: =IF('Lançamentos'!B14="","",'Lançamentos'!B14) | C22: =IF('Lançamentos'!C14="","",'Lançamentos'!C14) | D22: =IF('Lançamentos'!D14="","",'Lançamentos'!D14) | E22: =IF('Lançamentos'!E14="","",'Lançamentos'!E14) | F22: =IF('Lançamentos'!F14="","",'Lançamentos'!F14) | G22: =IF('Lançamentos'!G14="","",'Lançamentos'!G14)
A23: =IF('Lançamentos'!A15="","",'Lançamentos'!A15) | B23: =IF('Lançamentos'!B15="","",'Lançamentos'!B15) | C23: =IF('Lançamentos'!C15="","",'Lançamentos'!C15) | D23: =IF('Lançamentos'!D15="","",'Lançamentos'!D15) | E23: =IF('Lançamentos'!E15="","",'Lançamentos'!E15) | F23: =IF('Lançamentos'!F15="","",'Lançamentos'!F15) | G23: =IF('Lançamentos'!G15="","",'Lançamentos'!G15)
A24: =IF('Lançamentos'!A16="","",'Lançamentos'!A16) | B24: =IF('Lançamentos'!B16="","",'Lançamentos'!B16) | C24: =IF('Lançamentos'!C16="","",'Lançamentos'!C16) | D24: =IF('Lançamentos'!D16="","",'Lançamentos'!D16) | E24: =IF('Lançamentos'!E16="","",'Lançamentos'!E16) | F24: =IF('Lançamentos'!F16="","",'Lançamentos'!F16) | G24: =IF('Lançamentos'!G16="","",'Lançamentos'!G16)
A25: =IF('Lançamentos'!A17="","",'Lançamentos'!A17) | B25: =IF('Lançamentos'!B17="","",'Lançamentos'!B17) | C25: =IF('Lançamentos'!C17="","",'Lançamentos'!C17) | D25: =IF('Lançamentos'!D17="","",'Lançamentos'!D17) | E25: =IF('Lançamentos'!E17="","",'Lançamentos'!E17) | F25: =IF('Lançamentos'!F17="","",'Lançamentos'!F17) | G25: =IF('Lançamentos'!G17="","",'Lançamentos'!G17)
A26: =IF('Lançamentos'!A18="","",'Lançamentos'!A18) | B26: =IF('Lançamentos'!B18="","",'Lançamentos'!B18) | C26: =IF('Lançamentos'!C18="","",'Lançamentos'!C18) | D26: =IF('Lançamentos'!D18="","",'Lançamentos'!D18) | E26: =IF('Lançamentos'!E18="","",'Lançamentos'!E18) | F26: =IF('Lançamentos'!F18="","",'Lançamentos'!F18) | G26: =IF('Lançamentos'!G18="","",'Lançamentos'!G18)
A27: =IF('Lançamentos'!A19="","",'Lançamentos'!A19) | B27: =IF('Lançamentos'!B19="","",'Lançamentos'!B19) | C27: =IF('Lançamentos'!C19="","",'Lançamentos'!C19) | D27: =IF('Lançamentos'!D19="","",'Lançamentos'!D19) | E27: =IF('Lançamentos'!E19="","",'Lançamentos'!E19) | F27: =IF('Lançamentos'!F19="","",'Lançamentos'!F19) | G27: =IF('Lançamentos'!G19="","",'Lançamentos'!G19)
A28: =IF('Lançamentos'!A20="","",'Lançamentos'!A20) | B28: =IF('Lançamentos'!B20="","",'Lançamentos'!B20) | C28: =IF('Lançamentos'!C20="","",'Lançamentos'!C20) | D28: =IF('Lançamentos'!D20="","",'Lançamentos'!D20) | E28: =IF('Lançamentos'!E20="","",'Lançamentos'!E20) | F28: =IF('Lançamentos'!F20="","",'Lançamentos'!F20) | G28: =IF('Lançamentos'!G20="","",'Lançamentos'!G20)
A32: Visão Anual - 12 Meses
A33: Item | B33: Jan | C33: Fev | D33: Mar | E33: Abr | F33: Mai | G33: Jun | H33: Jul | I33: Ago | J33: Set | K33: Out | L33: Nov | M33: Dez | N33: Total Anual
A34: Receitas | B34: =SUMIFS('Lançamentos'!$E$3:$E$500, 'Lançamentos'!$D$3:$D$500, "Receita", 'Lançamentos'!$F$3:$F$500, B$33) | C34: =SUMIFS('Lançamentos'!$E$3:$E$500, 'Lançamentos'!$D$3:$D$500, "Receita", 'Lançamentos'!$F$3:$F$500, C$33) | D34: =SUMIFS('Lançamentos'!$E$3:$E$500, 'Lançamentos'!$D$3:$D$500, "Receita", 'Lançamentos'!$F$3:$F$500, D$33) | E34: =SUMIFS('Lançamentos'!$E$3:$E$500, 'Lançamentos'!$D$3:$D$500, "Receita", 'Lançamentos'!$F$3:$F$500, E$33) | F34: =SUMIFS('Lançamentos'!$E$3:$E$500, 'Lançamentos'!$D$3:$D$500, "Receita", 'Lançamentos'!$F$3:$F$500, F$33) | G34: =SUMIFS('Lançamentos'!$E$3:$E$500, 'Lançamentos'!$D$3:$D$500, "Receita", 'Lançamentos'!$F$3:$F$500, G$33) | H34: =SUMIFS('Lançamentos'!$E$3:$E$500, 'Lançamentos'!$D$3:$D$500, "Receita", 'Lançamentos'!$F$3:$F$500, H$33) | I34: =SUMIFS('Lançamentos'!$E$3:$E$500, 'Lançamentos'!$D$3:$D$500, "Receita", 'Lançamentos'!$F$3:$F$500, I$33) | ... M34: =SUMIFS('Lançamentos'!$E$3:$E$500, 'Lançamentos'!$D$3:$D$500, "Receita", 'Lançamentos'!$F$3:$F$500, M$33) | N34: =SUM(B34:M34)
A35: Despesas | B35: =SUMIFS('Lançamentos'!$E$3:$E$500, 'Lançamentos'!$D$3:$D$500, "Despesa", 'Lançamentos'!$F$3:$F$500, B$33) | C35: =SUMIFS('Lançamentos'!$E$3:$E$500, 'Lançamentos'!$D$3:$D$500, "Despesa", 'Lançamentos'!$F$3:$F$500, C$33) | D35: =SUMIFS('Lançamentos'!$E$3:$E$500, 'Lançamentos'!$D$3:$D$500, "Despesa", 'Lançamentos'!$F$3:$F$500, D$33) | E35: =SUMIFS('Lançamentos'!$E$3:$E$500, 'Lançamentos'!$D$3:$D$500, "Despesa", 'Lançamentos'!$F$3:$F$500, E$33) | F35: =SUMIFS('Lançamentos'!$E$3:$E$500, 'Lançamentos'!$D$3:$D$500, "Despesa", 'Lançamentos'!$F$3:$F$500, F$33) | G35: =SUMIFS('Lançamentos'!$E$3:$E$500, 'Lançamentos'!$D$3:$D$500, "Despesa", 'Lançamentos'!$F$3:$F$500, G$33) | H35: =SUMIFS('Lançamentos'!$E$3:$E$500, 'Lançamentos'!$D$3:$D$500, "Despesa", 'Lançamentos'!$F$3:$F$500, H$33) | I35: =SUMIFS('Lançamentos'!$E$3:$E$500, 'Lançamentos'!$D$3:$D$500, "Despesa", 'Lançamentos'!$F$3:$F$500, I$33) | ... M35: =SUMIFS('Lançamentos'!$E$3:$E$500, 'Lançamentos'!$D$3:$D$500, "Despesa", 'Lançamentos'!$F$3:$F$500, M$33) | N35: =SUM(B35:M35)
A36: Saldo do Mês | B36: =B34-B35 | C36: =C34-C35 | D36: =D34-D35 | E36: =E34-E35 | F36: =F34-F35 | G36: =G34-G35 | H36: =H34-H35 | I36: =I34-I35 | ... N36: =N34-N35
A37: Reserva do Mês | B37: =SUMIFS('Lançamentos'!$E$3:$E$500, 'Lançamentos'!$C$3:$C$500, "Reserva", 'Lançamentos'!$F$3:$F$500, B$33) | C37: =SUMIFS('Lançamentos'!$E$3:$E$500, 'Lançamentos'!$C$3:$C$500, "Reserva", 'Lançamentos'!$F$3:$F$500, C$33) | D37: =SUMIFS('Lançamentos'!$E$3:$E$500, 'Lançamentos'!$C$3:$C$500, "Reserva", 'Lançamentos'!$F$3:$F$500, D$33) | E37: =SUMIFS('Lançamentos'!$E$3:$E$500, 'Lançamentos'!$C$3:$C$500, "Reserva", 'Lançamentos'!$F$3:$F$500, E$33) | F37: =SUMIFS('Lançamentos'!$E$3:$E$500, 'Lançamentos'!$C$3:$C$500, "Reserva", 'Lançamentos'!$F$3:$F$500, F$33) | G37: =SUMIFS('Lançamentos'!$E$3:$E$500, 'Lançamentos'!$C$3:$C$500, "Reserva", 'Lançamentos'!$F$3:$F$500, G$33) | H37: =SUMIFS('Lançamentos'!$E$3:$E$500, 'Lançamentos'!$C$3:$C$500, "Reserva", 'Lançamentos'!$F$3:$F$500, H$33) | I37: =SUMIFS('Lançamentos'!$E$3:$E$500, 'Lançamentos'!$C$3:$C$500, "Reserva", 'Lançamentos'!$F$3:$F$500, I$33) | ... M37: =SUMIFS('Lançamentos'!$E$3:$E$500, 'Lançamentos'!$C$3:$C$500, "Reserva", 'Lançamentos'!$F$3:$F$500, M$33) | N37: =SUM(B37:M37)

Sheet Configurações
A1: Tipos de Lançamento | C1: Categorias | E1: Meses | G1: Filtro Mês | I1: Parâmetro | J1: Valor
A2: Receita | C2: Salário | E2: Jan | G2: Todos | I2: Meta Reserva (% Receitas) | J2: 0.2
A3: Despesa | C3: Rendas Extras | E3: Fev | G3: Jan
C4: Moradia | E4: Mar | G4: Fev
C5: Alimentação | E5: Abr | G5: Mar
C6: Transporte | E6: Mai | G6: Abr
C7: Estudos | E7: Jun | G7: Mai
C8: Saúde | E8: Jul | G8: Jun
C9: Lazer | E9: Ago | G9: Jul
C10: Reserva | E10: Set | G10: Ago
C11: Outras Despesas | E11: Out | G11: Set
E12: Nov | G12: Out
E13: Dez | G13: Nov
G14: Dez

Sheet Lançamentos
A1: Base de Lançamentos Financeiros
A2: Data | B2: Descrição | C2: Categoria | D2: Tipo | E2: Valor (R$) | F2: Mês | G2: Observações
A3: 05/01/2025 | B3: Salário - Empresa XPTO | C3: Salário | D3: Receita | E3: 4250 | F3: Jan | G3: Salário líquido
A4: 10/01/2025 | B4: Freelance - Consultoria RH | C4: Rendas Extras | D4: Receita | E4: 600 | F4: Jan | G4: Projeto de 5 dias
A5: 12/01/2025 | B5: Aluguel | C5: Moradia | D5: Despesa | E5: 1200 | F5: Jan | G5: Apartamento
A6: 15/01/2025 | B6: Supermercado Extra | C6: Alimentação | D6: Despesa | E6: 320.4 | F6: Jan | G6: Compras do mês
A7: 18/01/2025 | B7: Uber / 99 | C7: Transporte | D7: Despesa | E7: 87.6 | F7: Jan | G7: Deslocamentos
A8: 22/01/2025 | B8: Curso Online - Finanças | C8: Estudos | D8: Despesa | E8: 197 | F8: Jan | G8: Plataforma Alura
A9: 25/01/2025 | B9: Livro - Pai Rico, Pai Pobre | C9: Estudos | D9: Despesa | E9: 39.9 | F9: Jan | G9: Compra na Amazon
A10: 05/02/2025 | B10: Salário - Empresa XPTO | C10: Salário | D10: Receita | E10: 4250 | F10: Fev | G10: Salário líquido
A11: 10/02/2025 | B11: Freelance - Análise Planilhas | C11: Rendas Extras | D11: Receita | E11: 250 | F11: Fev | G11: Entrega de planilhas
A12: 12/02/2025 | B12: Academia Smart Fit | C12: Saúde | D12: Despesa | E12: 129.9 | F12: Fev | G12: Mensalidade
A13: 14/02/2025 | B13: Cinema - Final de Semana | C13: Lazer | D13: Despesa | E13: 78 | F13: Fev | G13: Ingressos + pipoca
A14: 20/02/2025 | B14: Transferência para Reserva | C14: Reserva | D14: Despesa | E14: 500 | F14: Fev | G14: Aplicação Nubank
... A20: 02/01/2025 | B20: Saldo Anterior Reserva | C20: Reserva | D20: Despesa | E20: 1500 | F20: Jan | G20: Reserva de emergência acumulada
